hybrid_vector_model/__init__.py
hybrid_vector_model/_autograd_ext.py
hybrid_vector_model/boater_movement_model.py
hybrid_vector_model/hybrid_vector_model.py
hybrid_vector_model/route_choice_model.py
hybrid_vector_model/statsutils.py
hybrid_vector_model/traveltime_model.py
hybrid_vector_model/Example/Edges.csv
hybrid_vector_model/Example/LakeData.csv
hybrid_vector_model/Example/PopulationData.csv
hybrid_vector_model/Example/PostalCodeAreas.csv
hybrid_vector_model/Example/SurveyData.csv
hybrid_vector_model/Example/TestGraph.pdf
hybrid_vector_model/Example/Vertices.csv
hybrid_vector_model/cvxpy_changes/LICENSE.txt
hybrid_vector_model/cvxpy_changes/cone_matrix_stuffing.py
hybrid_vector_model/cvxpy_changes/matrix_stuffing.py
hybrid_vector_model/cvxpy_changes/mosek_conif.py
hybrid_vector_model-0.9.0b9.dist-info/LICENSE
hybrid_vector_model-0.9.0b9.dist-info/METADATA
hybrid_vector_model-0.9.0b9.dist-info/WHEEL
hybrid_vector_model-0.9.0b9.dist-info/top_level.txt
hybrid_vector_model-0.9.0b9.dist-info/RECORD
