Metadata-Version: 2.1
Name: hybrid-vector-model
Version: 0.9.0b9
Summary: Package to model the traffic of invasive species and disease vectors
Home-page: https://github.com/vemomoto/vemomoto
Author: Samuel M. Fischer
License: LGPLv3
Project-URL: Bug Tracker, https://github.com/vemomoto/vemomoto/issues
Project-URL: Documentation, https://vemomoto.github.io/hybrid_vector_model
Project-URL: Source Code, https://github.com/vemomoto/vemomoto/tree/master/hybrid_vector_model
Project-URL: Publication, https://doi.org/10.1098/rsos.191858
Keywords: gravity model,hierarchical model,infectious disease,invasive species,propagule pressure
Classifier: License :: OSI Approved :: GNU Lesser General Public License v3 (LGPLv3)
Classifier: Development Status :: 4 - Beta
Classifier: Intended Audience :: Science/Research
Requires-Python: >=3.6
License-File: LICENSE
Requires-Dist: numpy
Requires-Dist: scipy
Requires-Dist: matplotlib
Requires-Dist: pandas
Requires-Dist: statsmodels
Requires-Dist: cvxpy
Requires-Dist: autograd
Requires-Dist: vemomoto-core-npcollections
Requires-Dist: numdifftools
Requires-Dist: vemomoto-core-tools (>=0.9.0.a4)
Requires-Dist: vemomoto-core-concurrent
Requires-Dist: lopaths (>=0.9.0.a5)
Requires-Dist: ci-rvm (>=0.10.0a0)
Provides-Extra: inspection_optimization
Requires-Dist: mosek ; extra == 'inspection_optimization'
